README.md
setup.py
multislsqp/__init__.py
multislsqp/_version.py
multislsqp/benchmarks.py
multislsqp/utils.py
multislsqp.egg-info/PKG-INFO
multislsqp.egg-info/SOURCES.txt
multislsqp.egg-info/dependency_links.txt
multislsqp.egg-info/requires.txt
multislsqp.egg-info/top_level.txt
multislsqp/scipy_14/__init__.py
multislsqp/scipy_14/slsqp.py
multislsqp/scipy_15/__init__.py
multislsqp/scipy_15/_differentiable_functions.py
multislsqp/scipy_15/_numdiff.py
multislsqp/scipy_15/optimize.py
multislsqp/scipy_15/slsqp.py
multislsqp/scipy_16/__init__.py
multislsqp/scipy_16/_differentiable_functions.py
multislsqp/scipy_16/_numdiff.py
multislsqp/scipy_16/optimize.py
multislsqp/scipy_16/slsqp.py
multislsqp/scipy_18/__init__.py
multislsqp/scipy_18/_differentiable_functions.py
multislsqp/scipy_18/_numdiff.py
multislsqp/scipy_18/optimize.py
multislsqp/scipy_18/slsqp.py