Metadata-Version: 2.1
Name: multislsqp
Version: 0.1.0
Summary: MultiSLSQP is an extension of the SLSQP algorithm used in scipy.optimize.minimize which supports multiple initial starting points.
Home-page: https://gitlab.com/RhydianL/multislsqp
Author: Rhydian Lewis
Author-email: rhydian.lewis@swansea.ac.uk
License: UNKNOWN
Platform: UNKNOWN
Classifier: Programming Language :: Python :: 3
Classifier: License :: OSI Approved :: MIT License
Classifier: Operating System :: OS Independent
Requires-Python: >=3.6
